{
    "Southeastern_Conference_Women's_Basketball_Player_of_the_Year": 1.0,
    "Nancy_Lieberman_Award": 0.3150684931506849,
    "Wade_Trophy": 0.3048780487804878,
    "Carol_Eckman_Award": 0.27710843373493976,
    "West_Coast_Conference_Women's_Basketball_Player_of_the_Year": 0.2569832402234637,
    "List_of_Senior_CLASS_Award_women's_basketball_winners": 0.2553191489361702,
    "SEC_Women's_Basketball_Tournament": 0.23694779116465864,
    "Big_East_Conference_Women's_Basketball_Player_of_the_Year": 0.2119815668202765,
    "USBWA_National_Freshman_of_the_Year": 0.18115942028985507,
    "Naismith_College_Player_of_the_Year": 0.16943521594684385,
    "Naismith_College_Coach_of_the_Year": 0.16666666666666666,
    "John_R._Wooden_Award": 0.15960912052117263,
    "Frances_Pomeroy_Naismith_Award": 0.1503267973856209,
    "Honda_Sports_Award": 0.08188976377952756,
    "DeLisha_Milton-Jones": 0.08146067415730338,
    "List_of_U.S._men's_college_basketball_national_player_of_the_year_awards": 0.043668122270742356,
    "List_of_Senior_CLASS_Award_men's_basketball_winners": 0.041811846689895474,
    "Clair_Bee_Coach_of_the_Year_Award": 0.040983606557377046,
    "Metro_Conference_Men's_Basketball_Player_of_the_Year": 0.04048582995951417,
    "Jim_Phelan_Award": 0.04032258064516129,
    "Pete_Newell_Big_Man_Award": 0.04,
    "Big_Eight_Conference_Men's_Basketball_Player_of_the_Year": 0.0392156862745098,
    "NABC_Defensive_Player_of_the_Year": 0.0390625,
    "UPI_College_Basketball_Coach_of_the_Year": 0.038461538461538464,
    "UPI_College_Basketball_Player_of_the_Year": 0.03802281368821293,
    "Adolph_Rupp_Trophy": 0.03731343283582089,
    "Southwest_Conference_Men's_Basketball_Player_of_the_Year": 0.03731343283582089,
    "NABC_Player_of_the_Year": 0.036101083032490974,
    "Henry_Iba_Award": 0.03597122302158273,
    "Associated_Press_College_Basketball_Player_of_the_Year": 0.035211267605633804,
    "Southwestern_Athletic_Conference_Men's_Basketball_Player_of_the_Year": 0.03508771929824561,
    "Oscar_Robertson_Trophy": 0.03508771929824561,
    "NABC_Coach_of_the_Year": 0.03484320557491289,
    "Mountain_West_Conference_Men's_Basketball_Player_of_the_Year": 0.034722222222222224,
    "The_Summit_League_Men's_Basketball_Player_of_the_Year": 0.034722222222222224,
    "Tamika_Catchings": 0.0345821325648415,
    "Sporting_News_Men's_College_Basketball_Player_of_the_Year": 0.034482758620689655,
    "Sun_Belt_Conference_Men's_Basketball_Player_of_the_Year": 0.03436426116838488,
    "Southland_Conference_Men's_Basketball_Player_of_the_Year": 0.03389830508474576,
    "Big_12_Conference_Men's_Basketball_Player_of_the_Year": 0.033783783783783786,
    "Patriot_League_Men's_Basketball_Player_of_the_Year": 0.03355704697986577,
    "Conference_USA_Men's_Basketball_Player_of_the_Year": 0.033444816053511704,
    "Southeastern_Conference_Men's_Basketball_Player_of_the_Year": 0.03323262839879154,
    "List_of_first_overall_WNBA_draft_picks": 0.03314917127071823,
    "Helms_Foundation_College_Basketball_Player_of_the_Year": 0.033112582781456956,
    "Haggerty_Award": 0.03257328990228013,
    "Western_Athletic_Conference_Men's_Basketball_Player_of_the_Year": 0.03257328990228013,
    "Southern_Conference_Men's_Basketball_Player_of_the_Year": 0.03215434083601286,
    "Big_South_Conference_Men's_Basketball_Player_of_the_Year": 0.03205128205128205,
    "Colonial_Athletic_Association_Men's_Basketball_Player_of_the_Year": 0.03184713375796178,
    "Colonial_Athletic_Association_Men's_Basketball_Coach_of_the_Year": 0.03184713375796178,
    "America_East_Conference_Men's_Basketball_Player_of_the_Year": 0.03164556962025317,
    "Metro_Atlantic_Athletic_Conference_Men's_Basketball_Player_of_the_Year": 0.03125,
    "Northeast_Conference_Men's_Basketball_Player_of_the_Year": 0.03125,
    "Horizon_League_Men's_Basketball_Player_of_the_Year": 0.03076923076923077,
    "Atlantic_Sun_Conference_Men's_Basketball_Player_of_the_Year": 0.03048780487804878,
    "Mid-Eastern_Athletic_Conference_Men's_Basketball_Player_of_the_Year": 0.03048780487804878,
    "Big_East_Conference_Men's_Basketball_Player_of_the_Year": 0.03003003003003003,
    "Missouri_Valley_Conference_Men's_Basketball_Player_of_the_Year": 0.03003003003003003,
    "Atlantic_10_Conference_Men's_Basketball_Player_of_the_Year": 0.029850746268656716,
    "Big_Sky_Conference_Men's_Basketball_Player_of_the_Year": 0.029498525073746312,
    "Big_West_Conference_Men's_Basketball_Player_of_the_Year": 0.02932551319648094,
    "NAIA_Basketball_Tournament_Most_Valuable_Player": 0.029154518950437316,
    "Missouri_Valley_Conference_Men's_Basketball_Coach_of_the_Year": 0.029154518950437316,
    "Ivy_League_Men's_Basketball_Player_of_the_Year": 0.028735632183908046,
    "Ticha_Penicheiro": 0.02849740932642487,
    "Atlantic_Coast_Conference_Men's_Basketball_Coach_of_the_Year": 0.028409090909090908,
    "Ohio_Valley_Conference_Men's_Basketball_Player_of_the_Year": 0.027624309392265192,
    "Mid-American_Conference_Men's_Basketball_Player_of_the_Year": 0.02717391304347826,
    "West_Coast_Conference_Men's_Basketball_Player_of_the_Year": 0.026954177897574125,
    "Atlantic_Coast_Conference_Men's_Basketball_Player_of_the_Year": 0.026525198938992044,
    "Yolanda_Griffith": 0.025510204081632654,
    "Pacific-12_Conference_Men's_Basketball_Player_of_the_Year": 0.02506265664160401,
    "Big_Ten_Conference_Men's_Basketball_Player_of_the_Year": 0.024875621890547265,
    "Dawn_Staley": 0.023157894736842106,
    "United_States_women's_national_basketball_team": 0.02286902286902287,
    "Lauren_Jackson": 0.022857142857142857,
    "Sue_Bird": 0.02106430155210643,
    "1989_NCAA_Women's_Division_I_Basketball_Tournament": 0.017937219730941704,
    "Taj_McWilliams-Franklin": 0.01680672268907563,
    "1996_NCAA_Women's_Division_I_Basketball_Tournament": 0.015463917525773196,
    "2008_NCAA_Women's_Division_I_Basketball_Tournament": 0.015228426395939087,
    "List_of_Women's_National_Basketball_Association_season_rebounding_leaders": 0.01507537688442211,
    "WNBA_Most_Valuable_Player_Award": 0.014705882352941176,
    "Naismith_Prep_Player_of_the_Year_Award": 0.014354066985645933,
    "Lindsay_Whalen": 0.014150943396226415,
    "Tara_VanDerveer": 0.013903743315508022,
    "Carmelo_Anthony": 0.01366742596810934,
    "Tina_Thompson": 0.013664596273291925,
    "1987_NCAA_Women's_Division_I_Basketball_Tournament": 0.013513513513513514,
    "1997_NCAA_Women's_Division_I_Basketball_Tournament": 0.013392857142857142,
    "Pat_Summitt": 0.013358778625954198,
    "1998_NCAA_Women's_Division_I_Basketball_Tournament": 0.013333333333333334,
    "2013_Washington_Mystics_season": 0.01327433628318584,
    "1999_Washington_Mystics_season": 0.013215859030837005,
    "2008_Washington_Mystics_season": 0.013157894736842105,
    "2010_Washington_Mystics_season": 0.013157894736842105,
    "2004_Washington_Mystics_season": 0.013157894736842105,
    "2007_Washington_Mystics_season": 0.013157894736842105,
    "2005_Washington_Mystics_season": 0.013157894736842105,
    "2011_Washington_Mystics_season": 0.013157894736842105,
    "2009_Washington_Mystics_season": 0.013100436681222707,
    "2003_Washington_Mystics_season": 0.013100436681222707,
    "2006_Washington_Mystics_season": 0.013100436681222707,
    "Katie_Smith": 0.01306532663316583,
    "2002_Washington_Mystics_season": 0.012987012987012988,
    "2000_Washington_Mystics_season": 0.012987012987012988,
    "2001_Washington_Mystics_season": 0.012987012987012988,
    "2012_Los_Angeles_Sparks_season": 0.01293103448275862,
    "2013_Los_Angeles_Sparks_season": 0.012875536480686695,
    "WNBA_Finals_Most_Valuable_Player_Award": 0.01282051282051282,
    "1999_Los_Angeles_Sparks_season": 0.01282051282051282,
    "Joe_Smith_(basketball)": 0.01279317697228145,
    "2007_Los_Angeles_Sparks_season": 0.01276595744680851,
    "2010_Los_Angeles_Sparks_season": 0.01276595744680851,
    "2004_Los_Angeles_Sparks_season": 0.01276595744680851,
    "2005_Los_Angeles_Sparks_season": 0.01276595744680851,
    "2011_Los_Angeles_Sparks_season": 0.01276595744680851,
    "2009_Los_Angeles_Sparks_season": 0.012711864406779662,
    "2003_Los_Angeles_Sparks_season": 0.012711864406779662,
    "2000_Los_Angeles_Sparks_season": 0.012605042016806723,
    "2002_Los_Angeles_Sparks_season": 0.012295081967213115,
    "2001_Los_Angeles_Sparks_season": 0.012244897959183673,
    "Katie_Douglas": 0.012135922330097087,
    "Sparks\u2013Shock_brawl": 0.01195219123505976,
    "Edith_Cummings_Munson_Golf_Award": 0.011764705882352941,
    "Robert_V._Geasey_Trophy": 0.011210762331838564,
    "1997\u201398_Tennessee_Lady_Volunteers_basketball_team": 0.011194029850746268,
    "Becky_Hammon": 0.011061946902654867,
    "Mike_Thibault": 0.010869565217391304,
    "NCAA_Inspiration_Award": 0.010752688172043012,
    "Joanne_P._McCallie": 0.0106951871657754,
    "Chris_Webber": 0.010554089709762533,
    "Tree_Rollins": 0.01048951048951049,
    "1991_NCAA_Women's_Division_I_Basketball_Tournament": 0.010256410256410256
}