{
    "Barrington_Broadcasting": 1.0,
    "WLOS": 0.6081081081081081,
    "Fox_Sports_Networks": 0.30612244897959184,
    "KLVX": 0.0748502994011976,
    "Media_in_Hutchinson,_Kansas": 0.05844155844155844,
    "Media_in_Binghamton,_New_York": 0.053164556962025315,
    "WSPA-TV": 0.05291970802919708,
    "Media_in_Dodge_City,_Kansas": 0.05202312138728324,
    "Media_in_Garden_City,_Kansas": 0.05202312138728324,
    "KSTP-TV": 0.052,
    "Media_in_Hays,_Kansas": 0.05172413793103448,
    "Media_in_Great_Bend,_Kansas": 0.05172413793103448,
    "KAXT-CD": 0.05077262693156733,
    "KLAS-TV": 0.050434782608695654,
    "Media_in_Salina,_Kansas": 0.04864864864864865,
    "South_Carolina_Educational_Television": 0.048638132295719845,
    "WANN-CD": 0.04851752021563342,
    "Oregon_Public_Broadcasting": 0.04753820033955857,
    "Media_in_Oklahoma_City": 0.04740406320541761,
    "KYMA-DT": 0.045787545787545784,
    "Media_in_Nashville,_Tennessee": 0.0455531453362256,
    "KLMV-LD": 0.04507042253521127,
    "Smoky_Hills_Public_Television": 0.04468085106382979,
    "Media_in_Denver": 0.04439252336448598,
    "Media_in_Seattle": 0.0425531914893617,
    "Media_in_Wichita,_Kansas": 0.041379310344827586,
    "Media_in_Indianapolis": 0.04081632653061224,
    "List_of_television_stations_in_Massachusetts_(by_channel_number)": 0.040280210157618214,
    "List_of_television_stations_in_Massachusetts": 0.040280210157618214,
    "Media_in_Chicago": 0.0392156862745098,
    "Redding,_California": 0.03896103896103896,
    "West_Virginia_Public_Broadcasting": 0.037921348314606744,
    "Media_in_Topeka,_Kansas": 0.03666666666666667,
    "List_of_colleges_and_universities_in_New_York's_Capital_District": 0.03571428571428571,
    "Kentucky_Educational_Television": 0.035668789808917196,
    "NHK_World": 0.03537735849056604,
    "List_of_television_stations_in_Oregon": 0.03505535055350553,
    "Georgia_Public_Broadcasting": 0.034528552456839307,
    "Lake_Charles,_Louisiana": 0.03411513859275053,
    "LATV": 0.034026465028355386,
    "List_of_Canadian_television_stations_available_in_the_United_States": 0.034026465028355386,
    "AMGTV": 0.034026465028355386,
    "Mexicanal": 0.034026465028355386,
    "LeSEA": 0.034026465028355386,
    "Cornerstone_Television": 0.034026465028355386,
    "List_of_former_TheCoolTV_affiliates": 0.034026465028355386,
    "List_of_United_States_over-the-air_television_networks": 0.034026465028355386,
    "Jewelry_Television": 0.033962264150943396,
    "Toponymies_of_places_in_New_York's_Capital_District": 0.03386454183266932,
    "Media_in_Manhattan,_Kansas": 0.03363914373088685,
    "Media_in_New_York's_Capital_District": 0.03339882121807466,
    "Christian_Television_Network": 0.03272727272727273,
    "Heartland_(TV_network)": 0.03185840707964602,
    "WeatherNation_TV": 0.031825795644891124,
    "Media_in_Boston": 0.03130434782608696,
    "Media_in_Columbus,_Georgia": 0.03076923076923077,
    "KCET": 0.030707610146862484,
    "Media_in_Pittsburgh": 0.029906542056074768,
    "The_Disney_Afternoon": 0.029850746268656716,
    "PBJ_(TV_network)": 0.029556650246305417,
    "KHET": 0.029197080291970802,
    "Media_in_Jacksonville,_Florida": 0.02914798206278027,
    "GetTV": 0.02875399361022364,
    "World_(TV_channel)": 0.028125,
    "Prime_Time_Entertainment_Network": 0.028125,
    "Southwest_Florida": 0.02809917355371901,
    "List_of_tallest_buildings_in_Albany,_New_York": 0.02809917355371901,
    "ZUUS_Country": 0.027993779160186624,
    "Tuff_TV": 0.027993779160186624,
    "National_Register_of_Historic_Places_listings_in_Rensselaer_County,_New_York": 0.027914614121510674,
    "List_of_incorporated_places_in_New_York's_Capital_District": 0.027419354838709678,
    "Albany_International_Airport": 0.027243589743589744,
    "E._W._Scripps_Company": 0.02702702702702703,
    "List_of_United_States_stations_available_in_Canada": 0.02665876777251185,
    "Laredo\u2013Nuevo_Laredo": 0.026004728132387706,
    "List_of_UniM\u00e1s_affiliates": 0.025936599423631124,
    "List_of_former_Fox_television_affiliates": 0.025936599423631124,
    "List_of_former_NTA_Film_Network_affiliates_in_the_United_States": 0.025936599423631124,
    "List_of_Me-TV_affiliates": 0.025936599423631124,
    "List_of_Bounce_TV_affiliates": 0.025936599423631124,
    "List_of_Trinity_Broadcasting_Network_affiliates": 0.025936599423631124,
    "List_of_former_CBS_television_affiliates": 0.025936599423631124,
    "List_of_former_ABC_television_affiliates": 0.025936599423631124,
    "List_of_former_NBC_television_affiliates": 0.025936599423631124,
    "List_of_Telemundo_affiliates": 0.025936599423631124,
    "List_of_Azteca_Am\u00e9rica_affiliates": 0.025936599423631124,
    "List_of_Univision_affiliates": 0.025936599423631124,
    "List_of_America_One_affiliates": 0.025936599423631124,
    "SEC_TV": 0.02586206896551724,
    "Albany_County,_New_York": 0.02564102564102564,
    "Diane_Farr": 0.025477707006369428,
    "MTV2": 0.02482876712328767,
    "Full_Ginsburg": 0.024096385542168676,
    "List_of_mayors_of_Charleston,_South_Carolina": 0.023728813559322035,
    "Cozi_TV": 0.023622047244094488,
    "Family_Radio": 0.023255813953488372,
    "Live_Well_Network": 0.022946859903381644,
    "Sportsman_Channel": 0.022770398481973434,
    "Charleston_International_Airport": 0.022151898734177215,
    "List_of_television_stations_in_Manitoba": 0.022058823529411766,
    "The_'90s_Are_All_That": 0.021696252465483234,
    "List_of_MyNetworkTV_affiliates": 0.021634615384615384,
    "List_of_NBC_television_affiliates_(table)": 0.021634615384615384,
    "List_of_ABC_television_affiliates_(table)": 0.021634615384615384,
    "List_of_Fox_television_affiliates_(table)": 0.021634615384615384,
    "List_of_CBS_television_affiliates_(table)": 0.021634615384615384,
    "Boilermaker_Road_Race": 0.02142857142857143,
    "Regional_sports_network": 0.0210016155088853,
    "San_Diego\u2013Tijuana": 0.020512820512820513,
    "South_Dakota_Public_Broadcasting": 0.02010968921389397,
    "Hudson_River": 0.01995305164319249,
    "National_Register_of_Historic_Places_listings_in_Charleston,_South_Carolina": 0.019662921348314606,
    "Disney\u2013ABC_Television_Group": 0.01929824561403509,
    "List_of_people_from_Missoula,_Montana": 0.01904761904761905,
    "Media_in_Missoula,_Montana": 0.01904761904761905,
    "Fareed_Zakaria_GPS": 0.01875,
    "National_Distance_Running_Hall_of_Fame": 0.01875,
    "WBAB": 0.01809954751131222,
    "Movies!": 0.018018018018018018,
    "Entravision_Communications": 0.017738359201773836,
    "Cox_Radio": 0.017738359201773836,
    "Jetix": 0.01765650080256822,
    "List_of_former_UPN_affiliates": 0.01730769230769231,
    "Digital_Spy_Soap_Awards": 0.017241379310344827,
    "List_of_Pennsylvania_state_historical_markers_in_Blair_County": 0.017080745341614908,
    "List_of_Pennsylvania_state_historical_markers_in_Cambria_County": 0.017001545595054096,
    "Shaw_University": 0.01669449081803005,
    "List_of_mayors_of_Missoula,_Montana": 0.01662049861495845,
    "Deutsche_Welle": 0.016163793103448277,
    "Harrisburg,_Pennsylvania": 0.015116279069767442,
    "Fox_Television_Stations": 0.015027322404371584,
    "Apollo_Global_Management": 0.0150093808630394,
    "CNBC": 0.015005359056806002,
    "St._Augustine's_University": 0.014858841010401188,
    "List_of_Ring_of_Honor_alumni": 0.014492753623188406,
    "List_of_Ring_of_Honor_employees": 0.014492753623188406,
    "Larry_King_Now": 0.014124293785310734,
    "Erie_Canal": 0.014096185737976783,
    "List_of_Marie_episodes": 0.014005602240896359,
    "Laredo,_Texas": 0.013513513513513514,
    "The_Real_(TV_series)": 0.013477088948787063,
    "List_of_ROH_World_Champions": 0.013114754098360656,
    "List_of_The_Ellen_DeGeneres_Show_episodes": 0.01282051282051282,
    "John_Batchelor": 0.012578616352201259,
    "Nuevo_Laredo": 0.012437810945273632,
    "Squawk_Box": 0.012012012012012012,
    "The_View_(U.S._TV_series)": 0.011961722488038277,
    "The_Baseball_Network": 0.011659192825112108,
    "Washington\u2013Grizzly_Stadium": 0.011583011583011582,
    "List_of_late-night_American_network_TV_programs": 0.011406844106463879,
    "World_Basketball_League": 0.011320754716981131,
    "Raleigh,_North_Carolina": 0.01124859392575928,
    "Charleston_Battery": 0.0112,
    "List_of_ROH_World_Tag_Team_Champions": 0.011019283746556474,
    "Estrella_TV": 0.010869565217391304,
    "List_of_The_Late_Late_Show_with_Craig_Ferguson_episodes": 0.010752688172043012,
    "The_Late_Late_Show_with_Craig_Ferguson_(season_1)": 0.010752688172043012,
    "The_Late_Late_Show_with_Craig_Ferguson_(season_10)": 0.010752688172043012,
    "Quad_Cities": 0.010368663594470046,
    "GMT_(programme)": 0.0103359173126615,
    "Charlotte_Knights": 0.010086455331412104
}