{
    "List_of_state_routes_in_Washington": 1.0,
    "State_highways_in_Washington": 0.5,
    "1964_state_highway_renumbering_(Washington)": 0.2857142857142857,
    "Washington_State_Route_16": 0.25,
    "Washington_State_Route_3": 0.25,
    "Washington_State_Route_509": 0.25,
    "Washington_State_Route_9": 0.2,
    "Washington_State_Route_167": 0.16666666666666666,
    "Washington_State_Route_21": 0.16666666666666666,
    "Washington_State_Route_104": 0.16666666666666666,
    "Washington_State_Route_99": 0.14285714285714285,
    "Washington_State_Route_14": 0.125,
    "Washington_State_Route_17": 0.125,
    "Washington_State_Route_520": 0.125,
    "Washington_State_Route_522": 0.125,
    "Washington_State_Route_410": 0.1111111111111111,
    "Washington_State_Route_20": 0.07692307692307693
}