{
    "List_of_offsprings_of_Pop_Idol": 1.0,
    "Idols_(TV_series)": 1.0,
    "Celebrity_Big_Brother_5": 0.5,
    "Your_Face_Sounds_Familiar": 0.2,
    "Top_Model": 0.16666666666666666,
    "Cenla_Idol": 0.16666666666666666,
    "Arab_Idol_(season_2)": 0.16666666666666666,
    "1_vs._100": 0.16666666666666666,
    "The_Farm_(TV_series)": 0.14285714285714285,
    "List_of_American_television_shows_based_on_foreign_shows": 0.14285714285714285,
    "List_of_television_spin-offs": 0.14285714285714285,
    "List_of_television_game_show_franchises": 0.14285714285714285,
    "50\u201350_(game_show)": 0.14285714285714285,
    "Who_Wants_to_Be_a_Millionaire?": 0.14285714285714285,
    "Arab_Idol_(season_1)": 0.14285714285714285,
    "International_versions_of_Wheel_of_Fortune": 0.14285714285714285,
    "Deal_or_No_Deal": 0.125,
    "List_of_television_show_franchises": 0.125,
    "List_of_Idols_winners": 0.125,
    "Got_Talent": 0.125,
    "MasterChef": 0.125,
    "The_Apprentice_(TV_series)": 0.125,
    "List_of_television_programs_based_on_films": 0.125,
    "The_Price_Is_Right": 0.125,
    "Bigg_Boss": 0.125,
    "Survivor_(TV_series)": 0.125,
    "Walking_with...": 0.1111111111111111,
    "The_Office": 0.1111111111111111,
    "List_of_films_based_on_British_television_series": 0.1111111111111111,
    "List_of_films_based_on_television_programs": 0.1111111111111111,
    "CSI_(franchise)": 0.1,
    "The_X_Factor_(TV_series)": 0.1,
    "The_Biggest_Loser": 0.1,
    "Pets_(TV_series)": 0.09090909090909091,
    "List_of_British_television_series_based_on_American_television_series": 0.09090909090909091,
    "The_Canterbury_Tales_(TV_series)": 0.09090909090909091,
    "Ben_10:_Secret_of_the_Omnitrix": 0.08333333333333333,
    "DC_animated_universe": 0.08333333333333333,
    "Jayann_Bautista": 0.08333333333333333,
    "Sea_Monsters_(TV_series)": 0.08333333333333333,
    "Ben_10": 0.08333333333333333,
    "Travel_Sick": 0.08333333333333333,
    "Farmer_Wants_a_Wife": 0.07692307692307693,
    "Twelve_Colonies": 0.07692307692307693,
    "Beverly_Hills,_90210_franchise": 0.07692307692307693,
    "Celebrity_Big_Brother_(UK)": 0.07692307692307693,
    "World_Idol": 0.07142857142857142,
    "Treasure_Hunt_(UK_game_show)": 0.07142857142857142,
    "Fort_Boyard_(TV_series)": 0.06896551724137931,
    "Dancing_on_Ice_around_the_world": 0.0625,
    "Junior_MasterChef": 0.058823529411764705,
    "Teachers_(UK_TV_series)": 0.058823529411764705,
    "Star_Trek": 0.05555555555555555,
    "The_Forsyte_Saga_(2002_miniseries)": 0.047619047619047616,
    "The_Forsyte_Saga:_To_Let": 0.047619047619047616,
    "Dallas_(2012_TV_series)": 0.047619047619047616,
    "Ghost_Whisperer": 0.04,
    "Private_Practice_(TV_series)": 0.03571428571428571,
    "Sit_Down,_Shut_Up_(2009_TV_series)": 0.034482758620689655,
    "The_Good_Wife": 0.034482758620689655,
    "Charlie_and_Lola_(TV_series)": 0.034482758620689655,
    "Hollywood_Squares": 0.03333333333333333,
    "Double_Dare_(1986_game_show)": 0.03125,
    "24_(TV_series)": 0.02631578947368421,
    "SpongeBob_SquarePants": 0.025
}