{
    "Hotter_Than_Hell_Tour": 1.0,
    "Kiss_Tour": 0.6666666666666666,
    "Nuthin'_Fancy_Tour": 0.5,
    "Sheer_Heart_Attack_Tour": 0.2857142857142857,
    "Dynasty_Tour": 0.25,
    "Love_Gun_Tour": 0.25,
    "Destroyer_Tour": 0.25,
    "Diamond_Dogs_Tour": 0.25,
    "Pink_Floyd_1974_tours": 0.25,
    "Wish_You_Were_Here_Tour": 0.25,
    "Sonic_Boom_Over_Europe_Tour": 0.25,
    "Rolling_Thunder_Revue": 0.2,
    "Asylum_Tour_(Kiss)": 0.2,
    "A_Night_at_the_Opera_Tour": 0.2,
    "The_Hottest_Show_on_Earth_Tour": 0.2,
    "Rock_&_Roll_Over_Tour": 0.2,
    "Bob_Dylan_and_The_Band_1974_Tour": 0.16666666666666666
}