{
    "Real_estate_in_Kenya": 1.0,
    "Case\u2013Shiller_index": 0.3300970873786408,
    "Undergraduate_real_estate_programs": 0.3300970873786408,
    "List_of_countries_by_home_ownership_rate": 0.27717391304347827,
    "Deputy_President_of_Kenya": 0.26740947075208915,
    "Graduate_real_estate_education": 0.26356589147286824,
    "List_of_Presidents_of_Kenya": 0.257372654155496,
    "List_of_heads_of_state_of_Kenya": 0.257372654155496,
    "List_of_hospitals_in_Kenya": 0.256,
    "Kenya_Defence_Forces": 0.24870466321243523,
    "National_Assembly_(Kenya)": 0.21670428893905191,
    "President_of_Kenya": 0.21476510067114093,
    "Counties_of_Kenya": 0.19672131147540983,
    "Cabinet_of_Kenya": 0.013574660633484163,
    "Spatial_planning": 0.011764705882352941,
    "Kenyan_general_election,_1997": 0.011428571428571429,
    "Megalopolis_(city_type)": 0.0111731843575419
}