{
    "List_of_Swedish_football_champions": 1.0,
    "Division_2_Norra": 0.5703703703703704,
    "Swedish_football_Division_2_S\u00f6dra": 0.5703703703703704,
    "List_of_football_clubs_in_Sweden_\u2013_B": 0.5703703703703704,
    "List_of_football_clubs_in_Sweden_\u2013_D": 0.5703703703703704,
    "List_of_football_clubs_in_Sweden_\u2013_E": 0.5703703703703704,
    "List_of_football_clubs_in_Sweden_\u2013_F": 0.5703703703703704,
    "List_of_football_clubs_in_Sweden_\u2013_G": 0.5703703703703704,
    "List_of_football_clubs_in_Sweden_\u2013_H": 0.5703703703703704,
    "List_of_football_clubs_in_Sweden_\u2013_I": 0.5703703703703704,
    "List_of_football_clubs_in_Sweden_\u2013_K": 0.5703703703703704,
    "List_of_football_clubs_in_Sweden_\u2013_L": 0.5703703703703704,
    "List_of_football_clubs_in_Sweden_\u2013_M": 0.5703703703703704,
    "List_of_football_clubs_in_Sweden_\u2013_S": 0.5703703703703704,
    "List_of_football_clubs_in_Sweden_\u2013_T": 0.5703703703703704,
    "List_of_football_clubs_in_Sweden_\u2013_V": 0.5703703703703704,
    "Kamratm\u00e4sterskapen": 0.5703703703703704,
    "Wicanderska_V\u00e4lg\u00f6renhetssk\u00f6lden": 0.5703703703703704,
    "Seasons_in_Swedish_football": 0.5273972602739726,
    "Elitettan": 0.4425287356321839,
    "List_of_English_football_champions": 0.43703703703703706,
    "List_of_Slovenian_football_champions": 0.43703703703703706,
    "List_of_football_stadiums_in_Sweden": 0.385,
    "List_of_football_clubs_in_Sweden": 0.3793103448275862,
    "List_of_foreign_Allsvenskan_players": 0.36492890995260663,
    "List_of_Greek_football_champions": 0.3390804597701149,
    "List_of_Finnish_football_champions": 0.3277777777777778,
    "List_of_Macedonian_football_champions": 0.3072916666666667,
    "List_of_Danish_football_champions": 0.29797979797979796,
    "List_of_Polish_football_champions": 0.295,
    "List_of_Soviet_and_Russian_football_champions": 0.28640776699029125,
    "Scanian_derbies": 0.27598566308243727,
    "List_of_East_German_football_champions": 0.27314814814814814,
    "Sweden_national_under-17_football_team": 0.25483870967741934,
    "List_of_Svenska_Cupen_winners": 0.23511904761904762,
    "Swedish_Football_Association": 0.2257142857142857,
    "List_of_Serbian_football_champions": 0.21851851851851853,
    "Damallsvenskan": 0.21727019498607242,
    "Swedish_Football_Division_1": 0.21584699453551912,
    "Swedish_Football_Division_1_Norra": 0.21584699453551912,
    "Swedish_Football_Division_1_S\u00f6dra": 0.21584699453551912,
    "Superettan": 0.21122994652406418,
    "List_of_Sweden_international_footballers": 0.21024258760107817,
    "List_of_Norwegian_football_league_champions": 0.20921985815602837,
    "List_of_Ukrainian_football_champions": 0.20068027210884354,
    "List_of_Spanish_football_champions": 0.19932432432432431,
    "List_of_Turkish_football_champions": 0.19471947194719472,
    "Sweden_national_under-21_football_team": 0.19362745098039216,
    "List_of_Italian_football_champions": 0.19155844155844157,
    "Allsvenskan": 0.18912529550827423,
    "List_of_Dutch_football_champions": 0.18098159509202455,
    "List_of_French_football_champions": 0.17771084337349397,
    "List_of_Belgian_football_champions": 0.17352941176470588,
    "Luxembourg_National_Division": 0.16483516483516483,
    "List_of_Hungarian_football_champions": 0.15733333333333333,
    "List_of_Romanian_football_champions": 0.13947990543735225,
    "Liga_I_Final_Tables": 0.13947990543735225,
    "List_of_German_football_champions": 0.1388235294117647,
    "List_of_Irish_football_champions": 0.11991869918699187,
    "League_of_Ireland": 0.11991869918699187,
    "Sweden_national_football_team": 0.10604026845637583,
    "Sweden_national_men's_squash_team": 0.04950495049504951,
    "Sweden_national_speedway_team": 0.04184100418410042,
    "Sweden_men's_national_junior_ice_hockey_team": 0.036101083032490974,
    "Sweden_national_basketball_team": 0.029850746268656716,
    "Sweden_national_rugby_league_team": 0.029239766081871343,
    "Sweden_men's_national_ice_hockey_team": 0.029154518950437316,
    "Sweden_at_the_Paralympics": 0.02518891687657431,
    "Sweden_national_bandy_team": 0.02518891687657431,
    "2012_Damallsvenskan": 0.022321428571428572,
    "Oberliga_Berlin_(1945\u201363)": 0.01838235294117647,
    "Sweden_at_the_Olympics": 0.018115942028985508,
    "S\u00fcdkreis-Liga": 0.017985611510791366,
    "Oberliga_West_(1947\u201363)": 0.01773049645390071,
    "Oberliga_S\u00fcdwest_(1945\u201363)": 0.017006802721088437,
    "2013_Landskrona_BoIS_season": 0.017006802721088437,
    "Mestaruussarja": 0.01680672268907563,
    "Oberliga_Nord_(1947\u201363)": 0.016339869281045753,
    "Divisiones_Regionales_de_F\u00fatbol": 0.016260162601626018,
    "Divisiones_Regionales_de_F\u00fatbol_in_the_Valencian_Community": 0.016194331983805668,
    "Divisiones_Regionales_de_F\u00fatbol_in_Galicia": 0.016194331983805668,
    "Divisiones_Regionales_de_F\u00fatbol_in_Asturias": 0.016194331983805668,
    "Divisiones_Regionales_de_F\u00fatbol_in_the_Region_of_Murcia": 0.016194331983805668,
    "Divisiones_Regionales_de_F\u00fatbol_in_Castilla-La_Mancha": 0.016194331983805668,
    "Divisiones_Regionales_de_F\u00fatbol_in_Extremadura": 0.016194331983805668,
    "Divisiones_Regionales_de_F\u00fatbol_in_Castile_and_Le\u00f3n": 0.016194331983805668,
    "Divisiones_Regionales_de_F\u00fatbol_in_Arag\u00f3n": 0.016194331983805668,
    "Divisiones_Regionales_de_F\u00fatbol_in_Andalusia": 0.016194331983805668,
    "Divisiones_Regionales_de_F\u00fatbol_in_Canary_Islands": 0.016194331983805668,
    "Divisiones_Regionales_de_F\u00fatbol_in_Balearic_Islands": 0.016194331983805668,
    "Divisiones_Regionales_de_F\u00fatbol_in_La_Rioja": 0.016194331983805668,
    "Austrian_Supercup": 0.016194331983805668,
    "Divisiones_Regionales_de_F\u00fatbol_in_Catalonia": 0.016194331983805668,
    "DDR-Liga": 0.016129032258064516,
    "Regionalliga_Berlin_(1963\u201374)": 0.016,
    "2012_in_Swedish_football": 0.015957446808510637,
    "2013_in_Swedish_football": 0.015789473684210527,
    "Kazakhstan_Premier_League": 0.015625,
    "2nd_Oberliga_West": 0.015503875968992248,
    "Regionalliga_West_(1963\u201374)": 0.01532567049808429,
    "DDR-Oberliga": 0.015197568389057751,
    "Malta_national_football_team": 0.0149812734082397,
    "Yugoslav_Third_League": 0.014814814814814815,
    "Croatian_Republic_Football_League": 0.014814814814814815,
    "Russian_Super_Cup": 0.014760147601476014,
    "2012_Swedish_Football_Division_2": 0.014705882352941176,
    "2nd_Oberliga_S\u00fcdwest": 0.014598540145985401,
    "Oberliga_Nordrhein": 0.014598540145985401,
    "Regionalliga_S\u00fcdwest_(1963\u201374)": 0.014545454545454545,
    "2012_Superettan": 0.014336917562724014,
    "Amateur-Oberliga_Berlin": 0.014234875444839857,
    "2013_Superettan": 0.014234875444839857,
    "Belarusian_Premier_League": 0.014204545454545454,
    "Trofeo_Federale": 0.014150943396226415,
    "Johan_Cruijff_Shield": 0.014134275618374558,
    "Regionalliga_Nord_(1963\u201374)": 0.014035087719298246,
    "Coppa_Titano": 0.014018691588785047,
    "Oberliga_Westfalen": 0.01384083044982699,
    "Oberliga_S\u00fcd_(1945\u201363)": 0.013812154696132596,
    "Primera_Catalana": 0.013793103448275862,
    "Georgian_Super_Cup": 0.013761467889908258,
    "Slovenian_Republic_Football_League": 0.013745704467353952,
    "Israel_national_under-17_football_team": 0.0136986301369863,
    "Soviet_Top_League": 0.01366120218579235,
    "NOFV-Oberliga_Mitte": 0.013651877133105802,
    "DFL-Supercup": 0.013651877133105802,
    "French_Football_Federation": 0.01358695652173913,
    "Eccellenza_Abruzzo": 0.013513513513513514,
    "Eccellenza_Sicily": 0.013513513513513514,
    "Eccellenza_Campania": 0.013513513513513514,
    "Oberliga_Nord": 0.013513513513513514,
    "Eccellenza_Calabria": 0.013513513513513514,
    "Eccellenza_Apulia": 0.013513513513513514,
    "Eccellenza_Liguria": 0.013513513513513514,
    "Eccellenza_Sardinia": 0.013513513513513514,
    "Eccellenza_Umbria": 0.013513513513513514,
    "Eccellenza_Molise": 0.013513513513513514,
    "Eccellenza_Piedmont_and_Aosta_Valley": 0.013513513513513514,
    "Ukrainian_Super_Cup": 0.013513513513513514,
    "Serbian_SuperLiga": 0.013477088948787063,
    "Moldovan_National_Division": 0.013468013468013467,
    "Prva_HNL": 0.013368983957219251,
    "LTV_Super_Cup": 0.013333333333333334,
    "1._Liga_Classic": 0.013201320132013201,
    "Switzerland_national_under-17_football_team": 0.013201320132013201,
    "Slovenian_Supercup": 0.013157894736842105,
    "Greece_national_under-21_football_team": 0.012987012987012988,
    "Belgian_Second_Division": 0.012987012987012988,
    "San_Marino_national_football_team": 0.01293103448275862,
    "Turkish_Super_Cup": 0.012861736334405145,
    "Campionato_Sammarinese_di_Calcio": 0.01282051282051282,
    "Luxembourg_Division_of_Honour": 0.01276595744680851,
    "Scottish_Premiership_(association_football)": 0.012755102040816327,
    "Faroe_Islands_Cup": 0.012711864406779662,
    "Austrian_Football_First_League": 0.012698412698412698,
    "Austrian_Cup": 0.012698412698412698,
    "TFF_First_League": 0.012698412698412698,
    "Austrian_Football_Bundesliga": 0.012658227848101266,
    "Russian_Cup_(football)": 0.012618296529968454,
    "Swiss_Women's_Cup": 0.012552301255230125,
    "2nd_Amateurliga_Bayern": 0.012539184952978056,
    "Divisiones_Regionales_de_F\u00fatbol_in_Navarre": 0.012539184952978056,
    "Russian_National_Football_League": 0.012539184952978056,
    "Soviet_Second_League": 0.012539184952978056,
    "Luxembourg_national_under-21_football_team": 0.0125,
    "Luxembourg_2._Division": 0.0125,
    "Luxembourg_3._Division": 0.0125,
    "Soviet_First_League": 0.0125,
    "Football_Superleague_of_Kosovo": 0.012422360248447204,
    "Yugoslav_Cup": 0.01238390092879257,
    "Russia_national_under-19_football_team": 0.01238390092879257,
    "Azerbaijan_Premier_League": 0.012376237623762377,
    "Serbia_national_under-19_football_team": 0.012345679012345678,
    "Serbia_national_under-21_football_team": 0.012307692307692308,
    "Troph\u00e9e_des_champions": 0.012195121951219513,
    "Polish_Cup": 0.012195121951219513,
    "Moldovan_Cup": 0.012145748987854251,
    "Andorra_national_football_team": 0.012145748987854251,
    "Serbian_First_League": 0.012121212121212121,
    "List_of_Landskrona_BoIS_players": 0.012096774193548387,
    "Moldova_national_under-17_football_team": 0.012096774193548387,
    "Moldova_national_under-19_football_team": 0.012096774193548387,
    "Swiss_Cup": 0.012084592145015106,
    "Moldova_national_under-21_football_team": 0.012048192771084338,
    "Belarusian_Cup": 0.012048192771084338,
    "Turkey_national_under-17_football_team": 0.012012012012012012,
    "Turkey_national_under-19_football_team": 0.012012012012012012,
    "Iceland_national_under-17_football_team": 0.012,
    "Iceland_national_under-19_football_team": 0.012,
    "Serie_A": 0.011990407673860911,
    "Tippeligaen": 0.011961722488038277,
    "Women's_football_in_East_Germany": 0.01195219123505976,
    "Estonian_Supercup": 0.01195219123505976,
    "Bundesliga": 0.011933174224343675,
    "Georgian_Cup": 0.011904761904761904,
    "Swiss_Super_League": 0.011904761904761904,
    "FDGB-Pokal": 0.011904761904761904,
    "Israeli_Premier_League": 0.011904761904761904,
    "Premier_League_of_Bosnia_and_Herzegovina": 0.011869436201780416,
    "Bulgarian_State_Football_Championship": 0.011869436201780416,
    "Moldova_national_football_team": 0.011857707509881422,
    "Slovenian_PrvaLiga": 0.011834319526627219,
    "Russian_Football_Premier_League": 0.01182033096926714,
    "Czech_Fourth_Division": 0.011811023622047244,
    "Oberliga_Baden-W\u00fcrttemberg": 0.011799410029498525,
    "Gambrinus_Liga": 0.011799410029498525,
    "Georgia_national_football_team": 0.011764705882352941,
    "Faroe_Islands_national_football_team": 0.011764705882352941,
    "Luxembourg_1._Division": 0.011764705882352941,
    "List_of_Israel_State_Cup_winners": 0.011695906432748537,
    "Armenian_Premier_League": 0.011682242990654205,
    "Lithuania_national_under-17_football_team": 0.011583011583011582,
    "Slovenia_national_under-17_football_team": 0.011583011583011582,
    "Russia_national_under-17_football_team": 0.011527377521613832,
    "2nd_Oberliga_S\u00fcd": 0.011494252873563218,
    "Bosnia_and_Herzegovina_national_under-19_football_team": 0.011494252873563218,
    "Regionalliga_S\u00fcd_(1963\u201374)": 0.011461318051575931,
    "Belarus_national_football_team": 0.011450381679389313,
    "Eerste_Divisie": 0.011428571428571429,
    "Hungary_national_under-17_football_team": 0.011406844106463879,
    "Kazakhstan_First_Division": 0.011406844106463879,
    "Football_Federation_of_Bosnia_and_Herzegovina": 0.011363636363636364,
    "Soviet_Union_national_under-21_football_team": 0.011299435028248588,
    "Liga_e_Par\u00eb": 0.011235955056179775,
    "Swiss_Challenge_League": 0.011235955056179775,
    "Romania_national_under-21_football_team": 0.011235955056179775,
    "Bohemian_Football_League": 0.011235955056179775,
    "3._Liga": 0.011204481792717087,
    "Belgian_Pro_League": 0.011160714285714286,
    "Albanian_Supercup": 0.011152416356877323,
    "Czechoslovak_First_League": 0.011142061281337047,
    "Belgian_Promotion": 0.011111111111111112,
    "Slovenian_Second_League": 0.011111111111111112,
    "Slovakia_national_under-17_football_team": 0.011111111111111112,
    "Slovakia_national_under-21_football_team": 0.01107011070110701,
    "Second_League_of_Serbia_and_Montenegro": 0.011049723756906077,
    "2011_Damallsvenskan": 0.011049723756906077,
    "Soviet_Cup": 0.011049723756906077,
    "Bulgarian_Supercup": 0.01098901098901099,
    "Kazakhstan_Cup": 0.01098901098901099,
    "Ligue_1": 0.010964912280701754,
    "2012_Swedish_football_Division_1": 0.01090909090909091,
    "Israel_national_under-21_football_team": 0.010899182561307902,
    "2013_Swedish_football_Division_1": 0.010869565217391304,
    "First_Macedonian_Football_League": 0.01084010840108401,
    "Latvian_Higher_League": 0.01078167115902965,
    "2012_Malm\u00f6_FF_season": 0.010752688172043012,
    "Scottish_Championship": 0.010723860589812333,
    "Moldovan_\"A\"_Division": 0.010714285714285714,
    "Slovenian_Football_Cup": 0.010714285714285714,
    "Denmark_national_under-19_football_team": 0.010676156583629894,
    "Denmark_national_under-17_football_team": 0.010676156583629894,
    "Cypriot_Fourth_Division": 0.010676156583629894,
    "2013_Malm\u00f6_FF_season": 0.010676156583629894,
    "Scottish_Premier_League": 0.010638297872340425,
    "Belarusian_Second_League": 0.010638297872340425,
    "Macedonian_Cup": 0.010638297872340425,
    "A_Lyga": 0.010610079575596816,
    "List_of_A_Championship_stadiums": 0.01060070671378092,
    "Scottish_League_Two": 0.010582010582010581,
    "Superleague_Greece": 0.010570824524312896,
    "Pirveli_Liga": 0.01056338028169014,
    "List_of_German_women's_football_champions": 0.01056338028169014,
    "Azerbaijan_national_football_team": 0.01056338028169014,
    "Czech_Republic_national_under-17_football_team": 0.010526315789473684,
    "Ukrainian_Second_League": 0.010526315789473684,
    "Belarusian_First_League": 0.010526315789473684,
    "Belgian_Super_Cup": 0.01048951048951049,
    "2013_Halmstads_BK_season": 0.01048951048951049,
    "Montenegrin_First_League": 0.010471204188481676,
    "Estonian_Cup": 0.010452961672473868,
    "Bulgarian_A_Football_Group": 0.010416666666666666,
    "Segunda_Divisi\u00f3n_B_Groups_1\u20134": 0.010416666666666666,
    "Veikkausliiga": 0.0103359173126615,
    "List_of_European_national_football_team_managers": 0.0103359173126615,
    "List_of_top-division_football_clubs_in_CONMEBOL_countries": 0.010309278350515464,
    "Tre\u0107a_HNL": 0.010238907849829351,
    "Latvian_Football_Cup": 0.01020408163265306,
    "Czech_2._Liga": 0.01020408163265306,
    "Scottish_League_One": 0.010178117048346057,
    "West_Asian_Football_Federation": 0.01015228426395939,
    "Azerbaijan_Cup": 0.010135135135135136,
    "Russian_Professional_Football_League": 0.010126582278481013,
    "UEFA": 0.010077519379844961,
    "Bulgaria_national_under-17_football_team": 0.010067114093959731,
    "Macedonia_national_football_team": 0.010067114093959731,
    "Latvian_First_League": 0.010067114093959731,
    "Eredivisie": 0.010040160642570281,
    "Netherlands_Football_League_Championship": 0.010040160642570281,
    "Azerbaijan_First_Division": 0.010033444816053512,
    "2012_Djurg\u00e5rdens_IF_season": 0.010033444816053512,
    "Lithuanian_Football_Cup": 0.010033444816053512,
    "Bulgaria_national_under-21_football_team": 0.010033444816053512
}